classmanagement/__init__.py
classmanagement/models/__init__.py
classmanagement/models/class.py
classmanagement/models/student.py
classmanagement-0.0.3.dist-info/METADATA
classmanagement-0.0.3.dist-info/WHEEL
classmanagement-0.0.3.dist-info/top_level.txt
classmanagement-0.0.3.dist-info/RECORD
