Metadata-Version: 2.1
Name: classmanagement
Version: 0.0.3
Summary: Class Management by Nguyễn Chí Thanh
Home-page: UNKNOWN
Author: Chi Thanh Nguyen
Author-email: tenchithanh@gmail.com
License: MIT
Keywords: Class_Management,ClassManagement,CManagement
Platform: UNKNOWN
